lisp_emulator/__init__.py
lisp_emulator/__main__.py
lisp_emulator/common_lisp.py
lisp_emulator-1.0.3.dist-info/METADATA
lisp_emulator-1.0.3.dist-info/WHEEL
lisp_emulator-1.0.3.dist-info/top_level.txt
lisp_emulator-1.0.3.dist-info/RECORD
