Metadata-Version: 2.1
Name: lisp-emulator
Version: 1.0.3
Summary: Emulate basic Lisp environment in python for educational reasons.
Home-page: UNKNOWN
Author: jonas
License: UNKNOWN
Platform: UNKNOWN
Classifier: Programming Language :: Python :: 3
Requires-Dist: pyfiglet
